mysqlx/__init__.py
mysqlx/authentication.py
mysqlx/charsets.py
mysqlx/connection.py
mysqlx/constants.py
mysqlx/crud.py
mysqlx/dbdoc.py
mysqlx/errorcode.py
mysqlx/errors.py
mysqlx/expr.py
mysqlx/helpers.py
mysqlx/logger.py
mysqlx/protocol.py
mysqlx/py.typed
mysqlx/result.py
mysqlx/statement.py
mysqlx/tls_ciphers.py
mysqlx/types.py
mysqlx/utils.py
mysqlx/version.py
mysqlx/locales/__init__.py
mysqlx/locales/eng/__init__.py
mysqlx/locales/eng/client_error.py
mysqlx/protobuf/__init__.py
mysqlx/protobuf/mysqlx_connection_pb2.py
mysqlx/protobuf/mysqlx_crud_pb2.py
mysqlx/protobuf/mysqlx_cursor_pb2.py
mysqlx/protobuf/mysqlx_datatypes_pb2.py
mysqlx/protobuf/mysqlx_expect_pb2.py
mysqlx/protobuf/mysqlx_expr_pb2.py
mysqlx/protobuf/mysqlx_notice_pb2.py
mysqlx/protobuf/mysqlx_pb2.py
mysqlx/protobuf/mysqlx_prepare_pb2.py
mysqlx/protobuf/mysqlx_resultset_pb2.py
mysqlx/protobuf/mysqlx_session_pb2.py
mysqlx/protobuf/mysqlx_sql_pb2.py
mysqlx_connector_python-9.5.0.dist-info/licenses/LICENSE.txt
mysqlx_connector_python-9.5.0.dist-info/METADATA
mysqlx_connector_python-9.5.0.dist-info/WHEEL
mysqlx_connector_python-9.5.0.dist-info/top_level.txt
mysqlx_connector_python-9.5.0.dist-info/RECORD
