Metadata-Version: 2.4
Name: mysqlx-connector-python
Version: 9.5.0
Summary: A Python driver which implements the X DevAPI, an Application Programming Interface for working with the MySQL Document Store.
Author: Oracle and/or its affiliates
Author-email: 
License: GNU GPLv2 (with FOSS License Exception)
Project-URL: Homepage, https://dev.mysql.com/doc/connector-python/en/
Project-URL: Documentation, https://dev.mysql.com/doc/connector-python/en/
Project-URL: Downloads, https://dev.mysql.com/downloads/connector/python/
Project-URL: Release Notes, https://dev.mysql.com/doc/relnotes/connector-python/en/
Project-URL: Source Code, https://github.com/mysql/mysql-connector-python
Project-URL: Bug System, https://bugs.mysql.com/
Project-URL: Slack, https://mysqlcommunity.slack.com/messages/connectors
Project-URL: Forums, https://forums.mysql.com/list.php?50
Project-URL: Blog, https://blogs.oracle.com/mysql/
Keywords: mysql,database,db,connector,driver,xdevapi,nosql,docstore
Classifier: Development Status :: 5 - Production/Stable
Classifier: Intended Audience :: Developers
Classifier: Intended Audience :: Education
Classifier: License :: OSI Approved :: GNU General Public License (GPL)
Classifier: Operating System :: MacOS :: MacOS X
Classifier: Operating System :: Microsoft :: Windows
Classifier: Operating System :: POSIX :: Linux
Classifier: Operating System :: Unix
Classifier: Programming Language :: Python :: 3
Classifier: Programming Language :: Python :: 3.10
Classifier: Programming Language :: Python :: 3.11
Classifier: Programming Language :: Python :: 3.12
Classifier: Programming Language :: Python :: 3.13
Classifier: Programming Language :: Python :: 3.14
Classifier: Topic :: Database
Classifier: Topic :: Software Development
Classifier: Topic :: Software Development :: Libraries :: Python Modules
Classifier: Typing :: Typed
Requires-Python: >=3.10
License-File: LICENSE.txt
Requires-Dist: protobuf==5.29.4
Provides-Extra: dns-srv
Requires-Dist: dnspython==2.6.1; extra == "dns-srv"
Provides-Extra: compression
Requires-Dist: lz4==4.4.4; extra == "compression"
Requires-Dist: zstandard==0.23.0; extra == "compression"
Dynamic: author
Dynamic: classifier
Dynamic: description
Dynamic: description-content-type
Dynamic: keywords
Dynamic: license
Dynamic: license-file
Dynamic: project-url
Dynamic: provides-extra
Dynamic: requires-dist
Dynamic: requires-python
Dynamic: summary
